[
  {
    "name" : "bull",
    "requirements": {
      "stats": {
        "hp": 0,
        "mana": 0,
        "move": 0
      },
    },
    "offensive_bonuses": {
      "damage_reduction": 0,
      "damage": 1.25,
      "attacks": 0,
      "dodge" : 0,
      "parry" : 0,
    }
  },
  {
    "name" : "crane",
    "requirements": {
      "stats": {
        "hp": 0,
        "mana": 0,
        "move": 0
      },
    },
    "offensive_bonuses": {
      "damage_reduction": 0,
      "damage": 1.25,
      "attacks": 0
    }
  },
  {
    "name" : "mongoose",
    "requirements": {
      "stats": {
        "hp": 0,
        "mana": 0,
        "move": 0
      },
    },
    "offensive_bonuses": {
      "damage_reduction": 0,
      "damage": 1.25,
      "attacks": 0
    }
  },
  {
    "name" : "viper",
    "requirements": {
      "stats": {
        "hp": 0,
        "mana": 0,
        "move": 0
      },
    },
    "offensive_bonuses": {
      "damage_reduction": 0,
      "damage": 0,
      "attacks": 2
    }
  }
]
