{
  "Name": "The Realm of Dread",
  "Creator": "mute",
  "Min_vnum": "550",
  "Max_vnum": "599",
  "Mobiles": [
    {
      "Vnum": 550,
      "Name": "lesser shadow",
      "Short_Description": "a lesser shadow",
      "Long_Description": "A dark shape lurks waiting to attack.\n\r",
      "Description": "Shadows and darkness flit before your eyes.\n\r",
      "Act_Flags": [
        1,
        4,
        32,
        4096,
        16384
      ],
      "Affected_Flags": [
        2,
        8,
        32,
        64,
        32768,
        65536,
        524288,
        1048576,
        4194304
      ],
      "Alignment": -750,
      "Level": 50,
      "Exp_Level": 5626,
      "Hitroll": 375,
      "Damroll": 375,
      "AC": -750,
      "HP": 22500,
      "Gold": 0,
      "Sex": 1
    },
    {
      "Vnum": 551,
      "Name": "shadow",
      "Short_Description": "a shadow",
      "Long_Description": "A dark shape lurks, waiting to attack\n\r",
      "Description": "Shadows and darkness flit before your eyes.\n\r",
      "Act_Flags": [
        1,
        4,
        32,
        4096,
        16384
      ],
      "Affected_Flags": [
        2,
        8,
        32,
        64,
        32768,
        65536,
        524288,
        1048576,
        4194304
      ],
      "Alignment": -750,
      "Level": 80,
      "Exp_Level": 7500,
      "Hitroll": 500,
      "Damroll": 500,
      "AC": -1000,
      "HP": 30000,
      "Gold": 0,
      "Sex": 2
    },
    {
      "Vnum": 552,
      "Name": "greater shadow",
      "Short_Description": "a greater shadow",
      "Long_Description": "A dark shapes lurks ready to attack.\n\r",
      "Description": "Shadows and darkness flit before your eyes.\n\r",
      "Act_Flags": [
        1,
        4,
        32,
        4096,
        16384
      ],
      "Affected_Flags": [
        2,
        8,
        32,
        64,
        128,
        8192,
        32768,
        65536,
        524288,
        1048576,
        4194304
      ],
      "Alignment": -1000,
      "Level": 150,
      "Exp_Level": 11250,
      "Hitroll": 750,
      "Damroll": 750,
      "AC": -1500,
      "HP": 30000,
      "Gold": 0,
      "Sex": 1
    },
    {
      "Vnum": 553,
      "Name": "shadow guard",
      "Short_Description": "a shadow guardian",
      "Long_Description": "A dark shape lurks waiting to attack\n\r",
      "Description": "Shadows and darkness flit before your eyes.\n\r",
      "Act_Flags": [
        1,
        4,
        32,
        4096,
        16384
      ],
      "Affected_Flags": [
        2,
        8,
        32,
        64,
        32768,
        65536,
        524288,
        1048576,
        4194304
      ],
      "Alignment": -750,
      "Level": 130,
      "Exp_Level": 11249,
      "Hitroll": 750,
      "Damroll": 750,
      "AC": -1500,
      "HP": 30000,
      "Gold": 0,
      "Sex": 2
    },
    {
      "Vnum": 554,
      "Name": "shadow lord",
      "Short_Description": "a shadow lord",
      "Long_Description": "A dark shape lurks, waiting to attack.\n\r",
      "Description": "Shadows and darkness flit before your eyes.\n\r",
      "Act_Flags": [
        1,
        4,
        32,
        4096,
        16384
      ],
      "Affected_Flags": [
        2,
        8,
        32,
        64,
        128,
        8192,
        32768,
        65536,
        524288,
        1048576,
        4194304
      ],
      "Alignment": -750,
      "Level": 170,
      "Exp_Level": 11250,
      "Hitroll": 750,
      "Damroll": 750,
      "AC": -1500,
      "HP": 30000,
      "Gold": 0,
      "Sex": 1
    },
    {
      "Vnum": 555,
      "Name": "dread minion",
      "Short_Description": "a Dread minion",
      "Long_Description": "A dark shape, closes in for the kill\n\r",
      "Description": "Shadows and darkness flit before your eyes.\n\r",
      "Act_Flags": [
        1,
        4,
        32,
        4096,
        16384
      ],
      "Affected_Flags": [
        2,
        8,
        32,
        64,
        32768,
        65536,
        524288,
        1048576,
        4194304
      ],
      "Alignment": -500,
      "Level": 100,
      "Exp_Level": 9376,
      "Hitroll": 625,
      "Damroll": 625,
      "AC": -1250,
      "HP": 30000,
      "Gold": 0,
      "Sex": 2
    },
    {
      "Vnum": 556,
      "Name": "greater dread",
      "Short_Description": "a greater Dread",
      "Long_Description": "A dark shape moves in for the kill\n\r",
      "Description": "Shadows and darkness flit before your eyes.\n\r",
      "Act_Flags": [
        1,
        4,
        32,
        4096,
        16384
      ],
      "Affected_Flags": [
        2,
        8,
        32,
        64,
        32768,
        65536,
        524288,
        1048576,
        4194304
      ],
      "Alignment": -500,
      "Level": 160,
      "Exp_Level": 11250,
      "Hitroll": 750,
      "Damroll": 750,
      "AC": -1500,
      "HP": 30000,
      "Gold": 0,
      "Sex": 2
    },
    {
      "Vnum": 557,
      "Name": "lesser dread",
      "Short_Description": "a lesser Dread",
      "Long_Description": "A dark shape closes in for the kill\n\r",
      "Description": "Shadows and darkness flit before your eyes.\n\r",
      "Act_Flags": [
        1,
        4,
        32,
        4096,
        16384
      ],
      "Affected_Flags": [
        2,
        8,
        32,
        64,
        32768,
        65536,
        524288,
        1048576,
        4194304
      ],
      "Alignment": -500,
      "Level": 95,
      "Exp_Level": 9000,
      "Hitroll": 600,
      "Damroll": 600,
      "AC": -1200,
      "HP": 30000,
      "Gold": 0,
      "Sex": 2
    },
    {
      "Vnum": 558,
      "Name": "dread master",
      "Short_Description": "a Dread master",
      "Long_Description": "A dark shape closes in for the kill\n\r",
      "Description": "Shadows and darkness flit before your eyes.\n\r",
      "Act_Flags": [
        1,
        4,
        32,
        4096,
        16384
      ],
      "Affected_Flags": [
        2,
        8,
        32,
        64,
        128,
        8192,
        32768,
        65536,
        524288,
        1048576,
        4194304
      ],
      "Alignment": -750,
      "Level": 200,
      "Exp_Level": 13124,
      "Hitroll": 875,
      "Damroll": 875,
      "AC": -1750,
      "HP": 30000,
      "Gold": 0,
      "Sex": 1
    },
    {
      "Vnum": 559,
      "Name": "dread lord",
      "Short_Description": "a Dread Lord",
      "Long_Description": "A dark shape closes in for the kill\n\r",
      "Description": "Shadows and darkness flit before your eyes.\n\r",
      "Act_Flags": [
        1,
        4,
        32,
        4096,
        16384
      ],
      "Affected_Flags": [
        2,
        8,
        32,
        64,
        128,
        8192,
        32768,
        65536,
        524288,
        1048576,
        4194304
      ],
      "Alignment": -500,
      "Level": 250,
      "Exp_Level": 18751,
      "Hitroll": 1000,
      "Damroll": 1000,
      "AC": -2000,
      "HP": 30000,
      "Gold": 0,
      "Sex": 1
    },
    {
      "Vnum": 560,
      "Name": "dread guard",
      "Short_Description": "a Dread guard",
      "Long_Description": "A dark shape moves in to attack\n\r",
      "Description": "Shadows and darkness flit before your eyes.\n\r",
      "Act_Flags": [
        1,
        4,
        32,
        4096,
        16384
      ],
      "Affected_Flags": [
        2,
        8,
        32,
        64,
        32768,
        65536,
        524288,
        1048576,
        4194304
      ],
      "Alignment": -750,
      "Level": 140,
      "Exp_Level": 13124,
      "Hitroll": 875,
      "Damroll": 875,
      "AC": -1750,
      "HP": 30000,
      "Gold": 0,
      "Sex": 2
    },
    {
      "Vnum": 561,
      "Name": "dread guardian",
      "Short_Description": "a Dread guardian",
      "Long_Description": "A dark shape moves closer to attack\n\r",
      "Description": "Shadows and darkness flit before your eyes.\n\r",
      "Act_Flags": [
        1,
        4,
        32,
        4096,
        16384
      ],
      "Affected_Flags": [
        2,
        8,
        32,
        64,
        32768,
        65536,
        524288,
        1048576,
        4194304
      ],
      "Alignment": -750,
      "Level": 150,
      "Exp_Level": 13124,
      "Hitroll": 875,
      "Damroll": 875,
      "AC": -1750,
      "HP": 30000,
      "Gold": 0,
      "Sex": 1
    },
    {
      "Vnum": 562,
      "Name": "dragon shadow",
      "Short_Description": "a shadow dragon",
      "Long_Description": "A dark shape moves in for the kill\n\r",
      "Description": "Shadows and darkness flit before your eyes.\n\r",
      "Act_Flags": [
        1,
        32,
        4096,
        16384
      ],
      "Affected_Flags": [
        2,
        8,
        32,
        64,
        128,
        8192,
        32768,
        65536,
        524288,
        1048576,
        4194304
      ],
      "Alignment": -500,
      "Level": 200,
      "Exp_Level": 13125,
      "Hitroll": 875,
      "Damroll": 875,
      "AC": -1750,
      "HP": 30000,
      "Gold": 0,
      "Sex": 1
    },
    {
      "Vnum": 563,
      "Name": "smoke dragon",
      "Short_Description": "a smoke dragon",
      "Long_Description": "A dark shapes hovers waiting to kill\n\r",
      "Description": "Shadows and darkness flit before your eyes.\n\r",
      "Act_Flags": [
        1,
        32,
        4096,
        16384
      ],
      "Affected_Flags": [
        2,
        8,
        32,
        64,
        128,
        8192,
        32768,
        65536,
        524288,
        1048576,
        4194304
      ],
      "Alignment": -500,
      "Level": 140,
      "Exp_Level": 11250,
      "Hitroll": 750,
      "Damroll": 750,
      "AC": -1500,
      "HP": 30000,
      "Gold": 0,
      "Sex": 2
    }
  ],
  "Objects": [
    {
      "Vnum": 550,
      "Name": "dagger shadow",
      "Short_Description": "a shadow dagger",
      "Description": "A patch of darkness lurks in the corner",
      "Item_Type": 5,
      "Extra_Flags": [
        32,
        128,
        512,
        4096,
        32768,
        262144
      ],
      "Wear_Flags": [
        1,
        8192
      ],
      "Value0": 53,
      "Value1": 1,
      "Value2": 6,
      "Value3": 11,
      "Weight": 5,
      "Cost": 0,
      "Affect_Data": [
        {
					"Location":	18,
					"Modifier":	0,
					"Min_modifier": -1,
					"Max_modifier": 5
				}, 
				{
					"Location":	19,
					"Modifier":	0,
					"Min_modifier": -1,
					"Max_modifier": 5
        },
        {
					"Location":	28,
					"Modifier":	0,
					"Min_modifier": -10,
					"Max_modifier": 20
				}
      ],
      "Extra_Descr_Data": [],
      "ChPowerOn": "",
      "ChPowerOff": "",
      "ChPowerUse": "",
      "VictPowerOn": "",
      "VictPowerOff": "",
      "VictPowerUse": "",
      "SpecType": 0,
      "SpecPower": 0
    },
    {
      "Vnum": 551,
      "Name": "sword shadow",
      "Short_Description": "a shadow sword",
      "Description": "A patch of darkness lurks in the corner",
      "Item_Type": 41,
      "Extra_Flags": [
        32,
        128,
        512,
        4096,
        32768,
        262144
      ],
      "Wear_Flags": [
        1,
        8192,
        65536
      ],
      "Value0": 34,
      "Value1": 1,
      "Value2": 6,
      "Value3": 1,
      "Weight": 5,
      "Cost": 0,
      "Affect_Data": [
        {
					"Location":	18,
					"Modifier":	0,
					"Min_modifier": -1,
					"Max_modifier": 5
				}, 
				{
					"Location":	19,
					"Modifier":	0,
					"Min_modifier": -1,
					"Max_modifier": 5
        },
        {
					"Location":	28,
					"Modifier":	0,
					"Min_modifier": -10,
					"Max_modifier": 20
				}
      ],
      "Extra_Descr_Data": [],
      "ChPowerOn": "",
      "ChPowerOff": "",
      "ChPowerUse": "",
      "VictPowerOn": "",
      "VictPowerOff": "",
      "VictPowerUse": "",
      "SpecType": 0,
      "SpecPower": 0
    },
    {
      "Vnum": 552,
      "Name": "sword shadow",
      "Short_Description": "a shadow sword",
      "Description": "A patch of darkness lurks in the corner",
      "Item_Type": 41,
      "Extra_Flags": [
        32,
        128,
        512,
        4096,
        32768,
        131072,
        262144
      ],
      "Wear_Flags": [
        1,
        8192,
        65536
      ],
      "Value0": 37,
      "Value1": 1,
      "Value2": 6,
      "Value3": 3,
      "Weight": 5,
      "Cost": 0,
      "Affect_Data": [
        {
					"Location":	18,
					"Modifier":	0,
					"Min_modifier": -1,
					"Max_modifier": 5
				}, 
				{
					"Location":	19,
					"Modifier":	0,
					"Min_modifier": -1,
					"Max_modifier": 5
        },
        {
					"Location":	28,
					"Modifier":	0,
					"Min_modifier": -10,
					"Max_modifier": 20
				}
      ],
      "Extra_Descr_Data": [],
      "ChPowerOn": "",
      "ChPowerOff": "",
      "ChPowerUse": "",
      "VictPowerOn": "",
      "VictPowerOff": "",
      "VictPowerUse": "",
      "SpecType": 0,
      "SpecPower": 0
    },
    {
      "Vnum": 553,
      "Name": "sword shadow",
      "Short_Description": "a shadow sword",
      "Description": "A patch of darkness lurks in the corner",
      "Item_Type": 41,
      "Extra_Flags": [
        32,
        128,
        512,
        4096,
        32768,
        131072,
        262144,
        1048576
      ],
      "Wear_Flags": [
        1,
        8192,
        65536
      ],
      "Value0": 67,
      "Value1": 1,
      "Value2": 6,
      "Value3": 3,
      "Weight": 5,
      "Cost": 0,
      "Affect_Data": [
        {
					"Location":	18,
					"Modifier":	0,
					"Min_modifier": -1,
					"Max_modifier": 5
				}, 
				{
					"Location":	19,
					"Modifier":	0,
					"Min_modifier": -1,
					"Max_modifier": 5
        },
        {
					"Location":	28,
					"Modifier":	0,
					"Min_modifier": -10,
					"Max_modifier": 20
				}
      ],
      "Extra_Descr_Data": [],
      "ChPowerOn": "",
      "ChPowerOff": "",
      "ChPowerUse": "",
      "VictPowerOn": "",
      "VictPowerOff": "",
      "VictPowerUse": "",
      "SpecType": 0,
      "SpecPower": 0
    },
    {
      "Vnum": 554,
      "Name": "cloak shadow",
      "Short_Description": "a cloak of shadows",
      "Description": "A patch of darkness lurks in the corner",
      "Item_Type": 9,
      "Extra_Flags": [
        32,
        128,
        512,
        4096,
        32768,
        262144
      ],
      "Wear_Flags": [
        1,
        1024
      ],
      "Value0": 6,
      "Value1": 0,
      "Value2": 0,
      "Value3": 0,
      "Weight": 5,
      "Cost": 0,
      "Affect_Data": [
        {
					"Location":	1,
					"Modifier":	0,
					"Min_modifier": -3,
					"Max_modifier": 3
				}, 
				{
					"Location":	2,
					"Modifier":	0,
					"Min_modifier": -3,
					"Max_modifier": 3
				}, 
				{
					"Location":	3,
					"Modifier":	0,
					"Min_modifier": -3,
					"Max_modifier": 3
				}, 
				{
					"Location":	4,
					"Modifier":	0,
					"Min_modifier": -3,
					"Max_modifier": 3
				}, 
				{
					"Location":	5,
					"Modifier":	0,
					"Min_modifier": -3,
					"Max_modifier": 3
				}, 
				{
					"Location":	12,
					"Modifier":	0,
					"Min_modifier": 0,
					"Max_modifier": 100
				}, 
				{
					"Location":	13,
					"Modifier":	0,
					"Min_modifier": 0,
					"Max_modifier": 100
				}, 
				{
					"Location":	14,
					"Modifier":	0,
					"Min_modifier": 0,
					"Max_modifier": 100
				}
      ],
      "Extra_Descr_Data": [],
      "ChPowerOn": "",
      "ChPowerOff": "",
      "ChPowerUse": "",
      "VictPowerOn": "",
      "VictPowerOff": "",
      "VictPowerUse": "",
      "SpecType": 0,
      "SpecPower": 0
    },
    {
      "Vnum": 555,
      "Name": "cloak shadow",
      "Short_Description": "a cloak of shadows",
      "Description": "A patch of darkness lurks in the corner",
      "Item_Type": 9,
      "Extra_Flags": [
        32,
        128,
        512,
        4096,
        32768,
        262144
      ],
      "Wear_Flags": [
        1,
        1024
      ],
      "Value0": 6,
      "Value1": 0,
      "Value2": 0,
      "Value3": 10,
      "Weight": 5,
      "Cost": 0,
      "Affect_Data": [
        {
					"Location":	1,
					"Modifier":	0,
					"Min_modifier": -3,
					"Max_modifier": 3
				}, 
				{
					"Location":	2,
					"Modifier":	0,
					"Min_modifier": -3,
					"Max_modifier": 3
				}, 
				{
					"Location":	3,
					"Modifier":	0,
					"Min_modifier": -3,
					"Max_modifier": 3
				}, 
				{
					"Location":	4,
					"Modifier":	0,
					"Min_modifier": -3,
					"Max_modifier": 3
				}, 
				{
					"Location":	5,
					"Modifier":	0,
					"Min_modifier": -3,
					"Max_modifier": 3
				}, 
				{
					"Location":	12,
					"Modifier":	0,
					"Min_modifier": 0,
					"Max_modifier": 100
				}, 
				{
					"Location":	13,
					"Modifier":	0,
					"Min_modifier": 0,
					"Max_modifier": 100
				}, 
				{
					"Location":	14,
					"Modifier":	0,
					"Min_modifier": 0,
					"Max_modifier": 100
				}
      ],
      "Extra_Descr_Data": [],
      "ChPowerOn": "",
      "ChPowerOff": "",
      "ChPowerUse": "",
      "VictPowerOn": "",
      "VictPowerOff": "",
      "VictPowerUse": "",
      "SpecType": 0,
      "SpecPower": 0
    },
    {
      "Vnum": 556,
      "Name": "cloak shadow",
      "Short_Description": "a cloak of shadows",
      "Description": "A patch of darkness lurks in the corner",
      "Item_Type": 9,
      "Extra_Flags": [
        32,
        128,
        512,
        4096,
        32768,
        131072,
        262144,
        1048576
      ],
      "Wear_Flags": [
        1,
        1024
      ],
      "Value0": 6,
      "Value1": 0,
      "Value2": 0,
      "Value3": 0,
      "Weight": 5,
      "Cost": 0,
      "Affect_Data": [
        {
					"Location":	1,
					"Modifier":	0,
					"Min_modifier": -3,
					"Max_modifier": 3
				}, 
				{
					"Location":	2,
					"Modifier":	0,
					"Min_modifier": -3,
					"Max_modifier": 3
				}, 
				{
					"Location":	3,
					"Modifier":	0,
					"Min_modifier": -3,
					"Max_modifier": 3
				}, 
				{
					"Location":	4,
					"Modifier":	0,
					"Min_modifier": -3,
					"Max_modifier": 3
				}, 
				{
					"Location":	5,
					"Modifier":	0,
					"Min_modifier": -3,
					"Max_modifier": 3
				}, 
				{
					"Location":	12,
					"Modifier":	0,
					"Min_modifier": 0,
					"Max_modifier": 100
				}, 
				{
					"Location":	13,
					"Modifier":	0,
					"Min_modifier": 0,
					"Max_modifier": 100
				}, 
				{
					"Location":	14,
					"Modifier":	0,
					"Min_modifier": 0,
					"Max_modifier": 100
				}
      ],
      "Extra_Descr_Data": [],
      "ChPowerOn": "",
      "ChPowerOff": "",
      "ChPowerUse": "",
      "VictPowerOn": "",
      "VictPowerOff": "",
      "VictPowerUse": "",
      "SpecType": 0,
      "SpecPower": 0
    },
    {
      "Vnum": 557,
      "Name": "ring shadow",
      "Short_Description": "a ring of shadows",
      "Description": "A patch of darkness lurks in the corner",
      "Item_Type": 9,
      "Extra_Flags": [
        32,
        128,
        512,
        4096,
        32768,
        262144
      ],
      "Wear_Flags": [
        1,
        2
      ],
      "Value0": 6,
      "Value1": 0,
      "Value2": 0,
      "Value3": 0,
      "Weight": 5,
      "Cost": 0,
      "Affect_Data": [
        {
					"Location":	1,
					"Modifier":	0,
					"Min_modifier": -3,
					"Max_modifier": 3
				}, 
				{
					"Location":	2,
					"Modifier":	0,
					"Min_modifier": -3,
					"Max_modifier": 3
				}, 
				{
					"Location":	3,
					"Modifier":	0,
					"Min_modifier": -3,
					"Max_modifier": 3
				}, 
				{
					"Location":	4,
					"Modifier":	0,
					"Min_modifier": -3,
					"Max_modifier": 3
				}, 
				{
					"Location":	5,
					"Modifier":	0,
					"Min_modifier": -3,
					"Max_modifier": 3
				}, 
				{
					"Location":	12,
					"Modifier":	0,
					"Min_modifier": 0,
					"Max_modifier": 100
				}, 
				{
					"Location":	13,
					"Modifier":	0,
					"Min_modifier": 0,
					"Max_modifier": 100
				}, 
				{
					"Location":	14,
					"Modifier":	0,
					"Min_modifier": 0,
					"Max_modifier": 100
        },
        {
					"Location":	24,
					"Modifier":	0,
					"Min_modifier": -2,
					"Max_modifier": 2
				}
      ],
      "Extra_Descr_Data": [],
      "ChPowerOn": "",
      "ChPowerOff": "",
      "ChPowerUse": "",
      "VictPowerOn": "",
      "VictPowerOff": "",
      "VictPowerUse": "",
      "SpecType": 0,
      "SpecPower": 0
    },
    {
      "Vnum": 558,
      "Name": "ring shadow",
      "Short_Description": "a ring of shadows",
      "Description": "A patch of darkness lurks in the corner",
      "Item_Type": 9,
      "Extra_Flags": [
        32,
        128,
        512,
        4096,
        32768,
        131072,
        262144,
        1048576
      ],
      "Wear_Flags": [
        1,
        2
      ],
      "Value0": 6,
      "Value1": 0,
      "Value2": 0,
      "Value3": 13,
      "Weight": 5,
      "Cost": 0,
      "Affect_Data": [
        {
					"Location":	1,
					"Modifier":	0,
					"Min_modifier": -3,
					"Max_modifier": 3
				}, 
				{
					"Location":	2,
					"Modifier":	0,
					"Min_modifier": -3,
					"Max_modifier": 3
				}, 
				{
					"Location":	3,
					"Modifier":	0,
					"Min_modifier": -3,
					"Max_modifier": 3
				}, 
				{
					"Location":	4,
					"Modifier":	0,
					"Min_modifier": -3,
					"Max_modifier": 3
				}, 
				{
					"Location":	5,
					"Modifier":	0,
					"Min_modifier": -3,
					"Max_modifier": 3
				}, 
				{
					"Location":	12,
					"Modifier":	0,
					"Min_modifier": 0,
					"Max_modifier": 100
				}, 
				{
					"Location":	13,
					"Modifier":	0,
					"Min_modifier": 0,
					"Max_modifier": 100
				}, 
				{
					"Location":	14,
					"Modifier":	0,
					"Min_modifier": 0,
					"Max_modifier": 100
        },
        {
					"Location":	24,
					"Modifier":	0,
					"Min_modifier": -2,
					"Max_modifier": 2
				}
      ],
      "Extra_Descr_Data": [],
      "ChPowerOn": "",
      "ChPowerOff": "",
      "ChPowerUse": "",
      "VictPowerOn": "",
      "VictPowerOff": "",
      "VictPowerUse": "",
      "SpecType": 0,
      "SpecPower": 0
    },
    {
      "Vnum": 559,
      "Name": "bracer shadow",
      "Short_Description": "a shadowy bracer",
      "Description": "A patch of darkness lurks in the corner",
      "Item_Type": 37,
      "Extra_Flags": [
        32,
        128,
        512,
        4096,
        32768,
        262144
      ],
      "Wear_Flags": [
        1,
        4096
      ],
      "Value0": 6,
      "Value1": 0,
      "Value2": 0,
      "Value3": 0,
      "Weight": 5,
      "Cost": 0,
      "Affect_Data": [
        {
					"Location":	1,
					"Modifier":	0,
					"Min_modifier": -3,
					"Max_modifier": 3
        },
        {
					"Location":	18,
					"Modifier":	0,
					"Min_modifier": -1,
					"Max_modifier": 5
				}, 
				{
					"Location":	19,
					"Modifier":	0,
					"Min_modifier": -1,
					"Max_modifier": 5
        },
        {
					"Location":	28,
					"Modifier":	0,
					"Min_modifier": -10,
					"Max_modifier": 20
				}
      ],
      "Extra_Descr_Data": [],
      "ChPowerOn": "",
      "ChPowerOff": "",
      "ChPowerUse": "",
      "VictPowerOn": "",
      "VictPowerOff": "",
      "VictPowerUse": "",
      "SpecType": 0,
      "SpecPower": 0
    },
    {
      "Vnum": 560,
      "Name": "bracer shadow",
      "Short_Description": "a shadowy bracer",
      "Description": "A patch of darkness lurks in the corner",
      "Item_Type": 37,
      "Extra_Flags": [
        32,
        128,
        512,
        4096,
        32768,
        131072,
        262144,
        1048576
      ],
      "Wear_Flags": [
        1,
        4096
      ],
      "Value0": 6,
      "Value1": 0,
      "Value2": 0,
      "Value3": 0,
      "Weight": 5,
      "Cost": 0,
      "Affect_Data": [
        {
					"Location":	1,
					"Modifier":	0,
					"Min_modifier": -3,
					"Max_modifier": 3
        },
        {
					"Location":	18,
					"Modifier":	0,
					"Min_modifier": -1,
					"Max_modifier": 5
				}, 
				{
					"Location":	19,
					"Modifier":	0,
					"Min_modifier": -1,
					"Max_modifier": 5
        },
        {
					"Location":	28,
					"Modifier":	0,
					"Min_modifier": -10,
					"Max_modifier": 20
				}
      ],
      "Extra_Descr_Data": [],
      "ChPowerOn": "",
      "ChPowerOff": "",
      "ChPowerUse": "",
      "VictPowerOn": "",
      "VictPowerOff": "",
      "VictPowerUse": "",
      "SpecType": 0,
      "SpecPower": 0
    },
    {
      "Vnum": 561,
      "Name": "ring shadow",
      "Short_Description": "a ring of shadows",
      "Description": "A patch of darkness lurks in the corner",
      "Item_Type": 9,
      "Extra_Flags": [
        32,
        128,
        512,
        4096,
        32768,
        262144
      ],
      "Wear_Flags": [
        1,
        2
      ],
      "Value0": 6,
      "Value1": 0,
      "Value2": 0,
      "Value3": 11,
      "Weight": 5,
      "Cost": 0,
      "Affect_Data": [
        {
					"Location":	1,
					"Modifier":	0,
					"Min_modifier": -3,
					"Max_modifier": 3
				}, 
				{
					"Location":	2,
					"Modifier":	0,
					"Min_modifier": -3,
					"Max_modifier": 3
				},
				{
					"Location":	3,
					"Modifier":	0,
					"Min_modifier": -3,
					"Max_modifier": 3
				}, 
				{
					"Location":	4,
					"Modifier":	0,
					"Min_modifier": -3,
					"Max_modifier": 3
				},
				{
					"Location":	5,
					"Modifier":	0,
					"Min_modifier": -3,
					"Max_modifier": 3
				},
				{
					"Location":	12,
					"Modifier":	0,
					"Min_modifier": 0,
					"Max_modifier": 100
				},
				{
					"Location":	13,
					"Modifier":	0,
					"Min_modifier": 0,
					"Max_modifier": 100
				}, 
				{
					"Location":	14,
					"Modifier":	0,
					"Min_modifier": 0,
					"Max_modifier": 100
        },
        {
					"Location":	24,
					"Modifier":	0,
					"Min_modifier": -2,
					"Max_modifier": 2
				}
      ],
      "Extra_Descr_Data": [],
      "ChPowerOn": "",
      "ChPowerOff": "",
      "ChPowerUse": "",
      "VictPowerOn": "",
      "VictPowerOff": "",
      "VictPowerUse": "",
      "SpecType": 0,
      "SpecPower": 0
    }
  ],
  "Rooms": [
    {
      "Vnum": 550,
      "Name": "The Realm of Dread",
      "Description": "All around you are shadows\n\r",
      "Area_Number": 0,
      "Room_Flags": [
        1,
        16,
        64,
        128,
        8192,
        16384,
        32768,
        65536,
        131072
      ],
      "Sector_Type": 1,
      "Exits": [
        {
          "Door": 0,
          "Vnum": 552,
          "Description": "",
          "Keyword": "",
          "Key": -1,
          "ExitInfo": []
        },
        {
          "Door": 1,
          "Vnum": 551,
          "Description": "",
          "Keyword": "",
          "Key": -1,
          "ExitInfo": []
        },
        {
          "Door": 2,
          "Vnum": 554,
          "Description": "",
          "Keyword": "",
          "Key": -1,
          "ExitInfo": []
        },
        {
          "Door": 3,
          "Vnum": 555,
          "Description": "",
          "Keyword": "",
          "Key": -1,
          "ExitInfo": []
        },
        {
          "Door": 4,
          "Vnum": 556,
          "Description": "",
          "Keyword": "",
          "Key": -1,
          "ExitInfo": []
        },
        {
          "Door": 5,
          "Vnum": 553,
          "Description": "",
          "Keyword": "",
          "Key": -1,
          "ExitInfo": []
        }
      ],
      "Extra_Descr_Data": [],
      "RoomText_Data": []
    },
    {
      "Vnum": 551,
      "Name": "The Realm of Dread",
      "Description": "All around you are shadows\n\r",
      "Area_Number": 0,
      "Room_Flags": [
        1,
        16,
        64,
        128,
        512,
        16384,
        32768,
        65536,
        131072
      ],
      "Sector_Type": 1,
      "Exits": [
        {
          "Door": 0,
          "Vnum": 601,
          "Description": "",
          "Keyword": "",
          "Key": -1,
          "ExitInfo": []
        },
        {
          "Door": 1,
          "Vnum": 1819,
          "Description": "",
          "Keyword": "",
          "Key": -1,
          "ExitInfo": []
        },
        {
          "Door": 2,
          "Vnum": 12001,
          "Description": "",
          "Keyword": "",
          "Key": -1,
          "ExitInfo": []
        },
        {
          "Door": 3,
          "Vnum": 8318,
          "Description": "",
          "Keyword": "",
          "Key": -1,
          "ExitInfo": []
        },
        {
          "Door": 4,
          "Vnum": 506,
          "Description": "",
          "Keyword": "",
          "Key": -1,
          "ExitInfo": []
        },
        {
          "Door": 5,
          "Vnum": 119,
          "Description": "",
          "Keyword": "",
          "Key": -1,
          "ExitInfo": []
        }
      ],
      "Extra_Descr_Data": [],
      "RoomText_Data": []
    },
    {
      "Vnum": 552,
      "Name": "The Realm of Dread",
      "Description": "All around you are shadows\n\r",
      "Area_Number": 0,
      "Room_Flags": [
        1,
        16,
        64,
        128,
        512,
        16384,
        32768,
        65536,
        131072
      ],
      "Sector_Type": 1,
      "Exits": [
        {
          "Door": 0,
          "Vnum": 24113,
          "Description": "",
          "Keyword": "",
          "Key": -1,
          "ExitInfo": []
        },
        {
          "Door": 1,
          "Vnum": 9141,
          "Description": "",
          "Keyword": "",
          "Key": -1,
          "ExitInfo": []
        },
        {
          "Door": 2,
          "Vnum": 1558,
          "Description": "",
          "Keyword": "",
          "Key": -1,
          "ExitInfo": []
        },
        {
          "Door": 3,
          "Vnum": 8615,
          "Description": "",
          "Keyword": "",
          "Key": -1,
          "ExitInfo": []
        },
        {
          "Door": 4,
          "Vnum": 5313,
          "Description": "",
          "Keyword": "",
          "Key": -1,
          "ExitInfo": []
        },
        {
          "Door": 5,
          "Vnum": 1128,
          "Description": "",
          "Keyword": "",
          "Key": -1,
          "ExitInfo": []
        }
      ],
      "Extra_Descr_Data": [],
      "RoomText_Data": []
    },
    {
      "Vnum": 553,
      "Name": "The Realm of Dread",
      "Description": "All around you are shadows\n\r",
      "Area_Number": 0,
      "Room_Flags": [
        1,
        16,
        64,
        128,
        512,
        16384,
        32768,
        65536,
        131072
      ],
      "Sector_Type": 1,
      "Exits": [
        {
          "Door": 0,
          "Vnum": 10019,
          "Description": "",
          "Keyword": "",
          "Key": -1,
          "ExitInfo": []
        },
        {
          "Door": 1,
          "Vnum": 5016,
          "Description": "",
          "Keyword": "",
          "Key": -1,
          "ExitInfo": []
        },
        {
          "Door": 2,
          "Vnum": 1563,
          "Description": "",
          "Keyword": "",
          "Key": -1,
          "ExitInfo": []
        },
        {
          "Door": 3,
          "Vnum": 4749,
          "Description": "",
          "Keyword": "",
          "Key": -1,
          "ExitInfo": []
        },
        {
          "Door": 4,
          "Vnum": 2125,
          "Description": "",
          "Keyword": "",
          "Key": -1,
          "ExitInfo": []
        },
        {
          "Door": 5,
          "Vnum": 938,
          "Description": "",
          "Keyword": "",
          "Key": -1,
          "ExitInfo": []
        }
      ],
      "Extra_Descr_Data": [],
      "RoomText_Data": []
    },
    {
      "Vnum": 554,
      "Name": "The Realm of Dread",
      "Description": "All around you are shadows\n\r",
      "Area_Number": 0,
      "Room_Flags": [
        1,
        16,
        64,
        128,
        512,
        16384,
        32768,
        65536,
        131072
      ],
      "Sector_Type": 1,
      "Exits": [
        {
          "Door": 0,
          "Vnum": 6020,
          "Description": "",
          "Keyword": "",
          "Key": -1,
          "ExitInfo": []
        },
        {
          "Door": 1,
          "Vnum": 2570,
          "Description": "",
          "Keyword": "",
          "Key": -1,
          "ExitInfo": []
        },
        {
          "Door": 2,
          "Vnum": 2565,
          "Description": "",
          "Keyword": "",
          "Key": -1,
          "ExitInfo": []
        },
        {
          "Door": 3,
          "Vnum": 2404,
          "Description": "",
          "Keyword": "",
          "Key": -1,
          "ExitInfo": []
        },
        {
          "Door": 4,
          "Vnum": 2494,
          "Description": "",
          "Keyword": "",
          "Key": -1,
          "ExitInfo": []
        },
        {
          "Door": 5,
          "Vnum": 25529,
          "Description": "",
          "Keyword": "",
          "Key": -1,
          "ExitInfo": []
        }
      ],
      "Extra_Descr_Data": [],
      "RoomText_Data": []
    },
    {
      "Vnum": 555,
      "Name": "The Realm of Dread",
      "Description": "All around you are shadows\n\r",
      "Area_Number": 0,
      "Room_Flags": [
        1,
        16,
        64,
        128,
        512,
        16384,
        32768,
        65536,
        131072
      ],
      "Sector_Type": 1,
      "Exits": [
        {
          "Door": 0,
          "Vnum": 4201,
          "Description": "",
          "Keyword": "",
          "Key": -1,
          "ExitInfo": []
        },
        {
          "Door": 1,
          "Vnum": 3515,
          "Description": "",
          "Keyword": "",
          "Key": -1,
          "ExitInfo": []
        },
        {
          "Door": 2,
          "Vnum": 8002,
          "Description": "",
          "Keyword": "",
          "Key": -1,
          "ExitInfo": []
        },
        {
          "Door": 3,
          "Vnum": 5122,
          "Description": "",
          "Keyword": "",
          "Key": -1,
          "ExitInfo": []
        },
        {
          "Door": 4,
          "Vnum": 5059,
          "Description": "",
          "Keyword": "",
          "Key": -1,
          "ExitInfo": []
        },
        {
          "Door": 5,
          "Vnum": 9506,
          "Description": "",
          "Keyword": "",
          "Key": -1,
          "ExitInfo": []
        }
      ],
      "Extra_Descr_Data": [],
      "RoomText_Data": []
    },
    {
      "Vnum": 556,
      "Name": "The Realm of Dread",
      "Description": "All around you are shadows\n\r",
      "Area_Number": 0,
      "Room_Flags": [
        1,
        16,
        64,
        128,
        512,
        16384,
        32768,
        65536,
        131072
      ],
      "Sector_Type": 1,
      "Exits": [
        {
          "Door": 0,
          "Vnum": 3369,
          "Description": "",
          "Keyword": "",
          "Key": -1,
          "ExitInfo": []
        },
        {
          "Door": 1,
          "Vnum": 2536,
          "Description": "",
          "Keyword": "",
          "Key": -1,
          "ExitInfo": []
        },
        {
          "Door": 2,
          "Vnum": 9522,
          "Description": "",
          "Keyword": "",
          "Key": -1,
          "ExitInfo": []
        },
        {
          "Door": 3,
          "Vnum": 2394,
          "Description": "",
          "Keyword": "",
          "Key": -1,
          "ExitInfo": []
        },
        {
          "Door": 4,
          "Vnum": 3394,
          "Description": "",
          "Keyword": "",
          "Key": -1,
          "ExitInfo": []
        },
        {
          "Door": 5,
          "Vnum": 2472,
          "Description": "",
          "Keyword": "",
          "Key": -1,
          "ExitInfo": []
        }
      ],
      "Extra_Descr_Data": [],
      "RoomText_Data": []
    },
    {
      "Vnum": 557,
      "Name": "The Realm of Dread",
      "Description": "All around you are shadows\n\r",
      "Area_Number": 0,
      "Room_Flags": [
        1,
        16,
        64,
        128,
        8192,
        16384,
        32768,
        65536,
        131072
      ],
      "Sector_Type": 1,
      "Exits": [
        {
          "Door": 0,
          "Vnum": 559,
          "Description": "",
          "Keyword": "",
          "Key": -1,
          "ExitInfo": []
        },
        {
          "Door": 1,
          "Vnum": 562,
          "Description": "",
          "Keyword": "",
          "Key": -1,
          "ExitInfo": []
        },
        {
          "Door": 2,
          "Vnum": 563,
          "Description": "",
          "Keyword": "",
          "Key": -1,
          "ExitInfo": []
        },
        {
          "Door": 3,
          "Vnum": 558,
          "Description": "",
          "Keyword": "",
          "Key": -1,
          "ExitInfo": []
        },
        {
          "Door": 4,
          "Vnum": 561,
          "Description": "",
          "Keyword": "",
          "Key": -1,
          "ExitInfo": []
        },
        {
          "Door": 5,
          "Vnum": 560,
          "Description": "",
          "Keyword": "",
          "Key": -1,
          "ExitInfo": []
        }
      ],
      "Extra_Descr_Data": [],
      "RoomText_Data": []
    },
    {
      "Vnum": 558,
      "Name": "The Realm of Dread",
      "Description": "All around you are shadows\n\r",
      "Area_Number": 0,
      "Room_Flags": [
        1,
        16,
        64,
        128,
        512,
        16384,
        32768,
        65536,
        131072
      ],
      "Sector_Type": 1,
      "Exits": [
        {
          "Door": 0,
          "Vnum": 2434,
          "Description": "",
          "Keyword": "",
          "Key": -1,
          "ExitInfo": []
        },
        {
          "Door": 1,
          "Vnum": 1392,
          "Description": "",
          "Keyword": "",
          "Key": -1,
          "ExitInfo": []
        },
        {
          "Door": 2,
          "Vnum": 9152,
          "Description": "",
          "Keyword": "",
          "Key": -1,
          "ExitInfo": []
        },
        {
          "Door": 3,
          "Vnum": 8303,
          "Description": "",
          "Keyword": "",
          "Key": -1,
          "ExitInfo": []
        },
        {
          "Door": 4,
          "Vnum": 24936,
          "Description": "",
          "Keyword": "",
          "Key": -1,
          "ExitInfo": []
        },
        {
          "Door": 5,
          "Vnum": 3014,
          "Description": "",
          "Keyword": "",
          "Key": -1,
          "ExitInfo": []
        }
      ],
      "Extra_Descr_Data": [],
      "RoomText_Data": []
    },
    {
      "Vnum": 559,
      "Name": "The Realm of Dread",
      "Description": "All around you are shadows\n\r",
      "Area_Number": 0,
      "Room_Flags": [
        1,
        16,
        64,
        128,
        512,
        16384,
        32768,
        65536,
        131072
      ],
      "Sector_Type": 1,
      "Exits": [
        {
          "Door": 0,
          "Vnum": 9345,
          "Description": "",
          "Keyword": "",
          "Key": -1,
          "ExitInfo": []
        },
        {
          "Door": 1,
          "Vnum": 9218,
          "Description": "",
          "Keyword": "",
          "Key": -1,
          "ExitInfo": []
        },
        {
          "Door": 2,
          "Vnum": 8903,
          "Description": "",
          "Keyword": "",
          "Key": -1,
          "ExitInfo": []
        },
        {
          "Door": 3,
          "Vnum": 7845,
          "Description": "",
          "Keyword": "",
          "Key": -1,
          "ExitInfo": []
        },
        {
          "Door": 4,
          "Vnum": 1037,
          "Description": "",
          "Keyword": "",
          "Key": -1,
          "ExitInfo": []
        },
        {
          "Door": 5,
          "Vnum": 5250,
          "Description": "",
          "Keyword": "",
          "Key": -1,
          "ExitInfo": []
        }
      ],
      "Extra_Descr_Data": [],
      "RoomText_Data": []
    },
    {
      "Vnum": 560,
      "Name": "The Realm of Dread",
      "Description": "All around you are shadows\n\r",
      "Area_Number": 0,
      "Room_Flags": [
        1,
        16,
        64,
        128,
        512,
        16384,
        32768,
        65536,
        131072
      ],
      "Sector_Type": 1,
      "Exits": [
        {
          "Door": 0,
          "Vnum": 7112,
          "Description": "",
          "Keyword": "",
          "Key": -1,
          "ExitInfo": []
        },
        {
          "Door": 1,
          "Vnum": 10108,
          "Description": "",
          "Keyword": "",
          "Key": -1,
          "ExitInfo": []
        },
        {
          "Door": 2,
          "Vnum": 5350,
          "Description": "",
          "Keyword": "",
          "Key": -1,
          "ExitInfo": []
        },
        {
          "Door": 3,
          "Vnum": 6372,
          "Description": "",
          "Keyword": "",
          "Key": -1,
          "ExitInfo": []
        },
        {
          "Door": 4,
          "Vnum": 8741,
          "Description": "",
          "Keyword": "",
          "Key": -1,
          "ExitInfo": []
        },
        {
          "Door": 5,
          "Vnum": 4769,
          "Description": "",
          "Keyword": "",
          "Key": -1,
          "ExitInfo": []
        }
      ],
      "Extra_Descr_Data": [],
      "RoomText_Data": []
    },
    {
      "Vnum": 561,
      "Name": "The Realm of Dread",
      "Description": "All around you are shadows\n\r",
      "Area_Number": 0,
      "Room_Flags": [
        1,
        16,
        64,
        128,
        512,
        16384,
        32768,
        65536,
        131072
      ],
      "Sector_Type": 1,
      "Exits": [
        {
          "Door": 0,
          "Vnum": 2922,
          "Description": "",
          "Keyword": "",
          "Key": -1,
          "ExitInfo": []
        },
        {
          "Door": 1,
          "Vnum": 2216,
          "Description": "",
          "Keyword": "",
          "Key": -1,
          "ExitInfo": []
        },
        {
          "Door": 2,
          "Vnum": 10305,
          "Description": "",
          "Keyword": "",
          "Key": -1,
          "ExitInfo": []
        },
        {
          "Door": 3,
          "Vnum": 3700,
          "Description": "",
          "Keyword": "",
          "Key": -1,
          "ExitInfo": []
        },
        {
          "Door": 4,
          "Vnum": 3424,
          "Description": "",
          "Keyword": "",
          "Key": -1,
          "ExitInfo": []
        },
        {
          "Door": 5,
          "Vnum": 2904,
          "Description": "",
          "Keyword": "",
          "Key": -1,
          "ExitInfo": []
        }
      ],
      "Extra_Descr_Data": [],
      "RoomText_Data": []
    },
    {
      "Vnum": 562,
      "Name": "The Realm of Dread",
      "Description": "All around you are shadows\n\r",
      "Area_Number": 0,
      "Room_Flags": [
        1,
        16,
        64,
        128,
        512,
        16384,
        32768,
        65536,
        131072
      ],
      "Sector_Type": 1,
      "Exits": [
        {
          "Door": 0,
          "Vnum": 2208,
          "Description": "",
          "Keyword": "",
          "Key": -1,
          "ExitInfo": []
        },
        {
          "Door": 1,
          "Vnum": 3616,
          "Description": "",
          "Keyword": "",
          "Key": -1,
          "ExitInfo": []
        },
        {
          "Door": 2,
          "Vnum": 319,
          "Description": "",
          "Keyword": "",
          "Key": -1,
          "ExitInfo": []
        },
        {
          "Door": 3,
          "Vnum": 24054,
          "Description": "",
          "Keyword": "",
          "Key": -1,
          "ExitInfo": []
        },
        {
          "Door": 4,
          "Vnum": 7880,
          "Description": "",
          "Keyword": "",
          "Key": -1,
          "ExitInfo": []
        },
        {
          "Door": 5,
          "Vnum": 24195,
          "Description": "",
          "Keyword": "",
          "Key": -1,
          "ExitInfo": []
        }
      ],
      "Extra_Descr_Data": [],
      "RoomText_Data": []
    },
    {
      "Vnum": 563,
      "Name": "The Realm of Dread",
      "Description": "All around you are shadows\n\r",
      "Area_Number": 0,
      "Room_Flags": [
        1,
        16,
        64,
        128,
        512,
        16384,
        32768,
        65536,
        131072
      ],
      "Sector_Type": 1,
      "Exits": [
        {
          "Door": 0,
          "Vnum": 7201,
          "Description": "",
          "Keyword": "",
          "Key": -1,
          "ExitInfo": []
        },
        {
          "Door": 1,
          "Vnum": 5021,
          "Description": "",
          "Keyword": "",
          "Key": -1,
          "ExitInfo": []
        },
        {
          "Door": 2,
          "Vnum": 10080,
          "Description": "",
          "Keyword": "",
          "Key": -1,
          "ExitInfo": []
        },
        {
          "Door": 3,
          "Vnum": 6606,
          "Description": "",
          "Keyword": "",
          "Key": -1,
          "ExitInfo": []
        },
        {
          "Door": 4,
          "Vnum": 4065,
          "Description": "",
          "Keyword": "",
          "Key": -1,
          "ExitInfo": []
        },
        {
          "Door": 5,
          "Vnum": 5028,
          "Description": "",
          "Keyword": "",
          "Key": -1,
          "ExitInfo": []
        }
      ],
      "Extra_Descr_Data": [],
      "RoomText_Data": []
    }
  ],
  "Resets": [
    {
      "Command": "R",
      "Arg1": 551,
      "Arg2": 5,
      "Arg3": 0,
      "Comment": "; Randomize The Realm of Dread"
    },
    {
      "Command": "R",
      "Arg1": 550,
      "Arg2": 5,
      "Arg3": 0,
      "Comment": "; Randomize The Realm of Dread"
    },
    {
      "Command": "R",
      "Arg1": 552,
      "Arg2": 5,
      "Arg3": 0,
      "Comment": "; Randomize The Realm of Dread"
    },
    {
      "Command": "R",
      "Arg1": 553,
      "Arg2": 5,
      "Arg3": 0,
      "Comment": "; Randomize The Realm of Dread"
    },
    {
      "Command": "R",
      "Arg1": 554,
      "Arg2": 5,
      "Arg3": 0,
      "Comment": "; Randomize The Realm of Dread"
    },
    {
      "Command": "R",
      "Arg1": 555,
      "Arg2": 5,
      "Arg3": 0,
      "Comment": "; Randomize The Realm of Dread"
    },
    {
      "Command": "R",
      "Arg1": 556,
      "Arg2": 5,
      "Arg3": 0,
      "Comment": "; Randomize The Realm of Dread"
    },
    {
      "Command": "R",
      "Arg1": 557,
      "Arg2": 5,
      "Arg3": 0,
      "Comment": "; Randomize The Realm of Dread"
    },
    {
      "Command": "R",
      "Arg1": 558,
      "Arg2": 5,
      "Arg3": 0,
      "Comment": "; Randomize The Realm of Dread"
    },
    {
      "Command": "R",
      "Arg1": 559,
      "Arg2": 5,
      "Arg3": 0,
      "Comment": "; Randomize The Realm of Dread"
    },
    {
      "Command": "R",
      "Arg1": 560,
      "Arg2": 5,
      "Arg3": 0,
      "Comment": "; Randomize The Realm of Dread"
    },
    {
      "Command": "R",
      "Arg1": 561,
      "Arg2": 5,
      "Arg3": 0,
      "Comment": "; Randomize The Realm of Dread"
    },
    {
      "Command": "R",
      "Arg1": 562,
      "Arg2": 5,
      "Arg3": 0,
      "Comment": "; Randomize The Realm of Dread"
    },
    {
      "Command": "R",
      "Arg1": 563,
      "Arg2": 5,
      "Arg3": 0,
      "Comment": "; Randomize The Realm of Dread"
    },
    {
      "Command": "M",
      "Arg1": 550,
      "Arg2": 5,
      "Arg3": 550,
      "Comment": "a lesser shadow to The Realm of Dread"
    },
    {
      "Command": "E",
      "Arg1": 554,
      "Arg2": 100,
      "Arg3": 12,
      "Comment": ";"
    },
    {
      "Command": "E",
      "Arg1": 550,
      "Arg2": 100,
      "Arg3": 16,
      "Comment": ";"
    },
    {
      "Command": "M",
      "Arg1": 550,
      "Arg2": 5,
      "Arg3": 557,
      "Comment": "a lesser shadow to The Realm of Dread"
    },
    {
      "Command": "E",
      "Arg1": 554,
      "Arg2": 100,
      "Arg3": 12,
      "Comment": ";"
    },
    {
      "Command": "E",
      "Arg1": 550,
      "Arg2": 100,
      "Arg3": 16,
      "Comment": ";"
    },
    {
      "Command": "M",
      "Arg1": 551,
      "Arg2": 5,
      "Arg3": 550,
      "Comment": "a shadow to The Realm of Dread"
    },
    {
      "Command": "E",
      "Arg1": 554,
      "Arg2": 100,
      "Arg3": 12,
      "Comment": ";"
    },
    {
      "Command": "E",
      "Arg1": 550,
      "Arg2": 100,
      "Arg3": 16,
      "Comment": ";"
    },
    {
      "Command": "M",
      "Arg1": 551,
      "Arg2": 5,
      "Arg3": 557,
      "Comment": "a shadow to The Realm of Dread"
    },
    {
      "Command": "E",
      "Arg1": 554,
      "Arg2": 100,
      "Arg3": 12,
      "Comment": ";"
    },
    {
      "Command": "E",
      "Arg1": 550,
      "Arg2": 100,
      "Arg3": 16,
      "Comment": ";"
    },
    {
      "Command": "M",
      "Arg1": 552,
      "Arg2": 5,
      "Arg3": 550,
      "Comment": "a greater shadow to The Realm of Dread"
    },
    {
      "Command": "E",
      "Arg1": 555,
      "Arg2": 100,
      "Arg3": 12,
      "Comment": ";"
    },
    {
      "Command": "E",
      "Arg1": 552,
      "Arg2": 100,
      "Arg3": 16,
      "Comment": ";"
    },
    {
      "Command": "E",
      "Arg1": 557,
      "Arg2": 100,
      "Arg3": 1,
      "Comment": ";"
    },
    {
      "Command": "M",
      "Arg1": 552,
      "Arg2": 5,
      "Arg3": 557,
      "Comment": "a greater shadow to The Realm of Dread"
    },
    {
      "Command": "E",
      "Arg1": 555,
      "Arg2": 100,
      "Arg3": 12,
      "Comment": ";"
    },
    {
      "Command": "E",
      "Arg1": 552,
      "Arg2": 100,
      "Arg3": 16,
      "Comment": ";"
    },
    {
      "Command": "E",
      "Arg1": 557,
      "Arg2": 100,
      "Arg3": 1,
      "Comment": ";"
    },
    {
      "Command": "M",
      "Arg1": 553,
      "Arg2": 5,
      "Arg3": 550,
      "Comment": "a shadow guardian to The Realm of Dread"
    },
    {
      "Command": "E",
      "Arg1": 554,
      "Arg2": 100,
      "Arg3": 12,
      "Comment": ";"
    },
    {
      "Command": "E",
      "Arg1": 551,
      "Arg2": 100,
      "Arg3": 16,
      "Comment": ";"
    },
    {
      "Command": "M",
      "Arg1": 553,
      "Arg2": 5,
      "Arg3": 557,
      "Comment": "a shadow guardian to The Realm of Dread"
    },
    {
      "Command": "E",
      "Arg1": 554,
      "Arg2": 100,
      "Arg3": 12,
      "Comment": ";"
    },
    {
      "Command": "E",
      "Arg1": 551,
      "Arg2": 100,
      "Arg3": 16,
      "Comment": ";"
    },
    {
      "Command": "M",
      "Arg1": 554,
      "Arg2": 5,
      "Arg3": 550,
      "Comment": "a shadow lord to The Realm of Dread"
    },
    {
      "Command": "E",
      "Arg1": 558,
      "Arg2": 100,
      "Arg3": 1,
      "Comment": ";"
    },
    {
      "Command": "E",
      "Arg1": 556,
      "Arg2": 100,
      "Arg3": 12,
      "Comment": ";"
    },
    {
      "Command": "E",
      "Arg1": 553,
      "Arg2": 100,
      "Arg3": 16,
      "Comment": ";"
    },
    {
      "Command": "M",
      "Arg1": 554,
      "Arg2": 5,
      "Arg3": 557,
      "Comment": "a shadow lord to The Realm of Dread"
    },
    {
      "Command": "E",
      "Arg1": 558,
      "Arg2": 100,
      "Arg3": 1,
      "Comment": ";"
    },
    {
      "Command": "E",
      "Arg1": 556,
      "Arg2": 100,
      "Arg3": 12,
      "Comment": ";"
    },
    {
      "Command": "E",
      "Arg1": 553,
      "Arg2": 100,
      "Arg3": 16,
      "Comment": ";"
    },
    {
      "Command": "M",
      "Arg1": 555,
      "Arg2": 5,
      "Arg3": 550,
      "Comment": "a Dread minion to The Realm of Dread"
    },
    {
      "Command": "E",
      "Arg1": 554,
      "Arg2": 100,
      "Arg3": 12,
      "Comment": ";"
    },
    {
      "Command": "E",
      "Arg1": 550,
      "Arg2": 100,
      "Arg3": 16,
      "Comment": ";"
    },
    {
      "Command": "M",
      "Arg1": 555,
      "Arg2": 5,
      "Arg3": 557,
      "Comment": "a Dread minion to The Realm of Dread"
    },
    {
      "Command": "E",
      "Arg1": 554,
      "Arg2": 100,
      "Arg3": 12,
      "Comment": ";"
    },
    {
      "Command": "E",
      "Arg1": 550,
      "Arg2": 100,
      "Arg3": 16,
      "Comment": ";"
    },
    {
      "Command": "M",
      "Arg1": 556,
      "Arg2": 5,
      "Arg3": 550,
      "Comment": "a greater Dread to The Realm of Dread"
    },
    {
      "Command": "E",
      "Arg1": 557,
      "Arg2": 100,
      "Arg3": 1,
      "Comment": ";"
    },
    {
      "Command": "E",
      "Arg1": 555,
      "Arg2": 100,
      "Arg3": 12,
      "Comment": ";"
    },
    {
      "Command": "E",
      "Arg1": 552,
      "Arg2": 100,
      "Arg3": 16,
      "Comment": ";"
    },
    {
      "Command": "M",
      "Arg1": 556,
      "Arg2": 5,
      "Arg3": 557,
      "Comment": "a greater Dread to The Realm of Dread"
    },
    {
      "Command": "E",
      "Arg1": 557,
      "Arg2": 100,
      "Arg3": 1,
      "Comment": ";"
    },
    {
      "Command": "E",
      "Arg1": 555,
      "Arg2": 100,
      "Arg3": 12,
      "Comment": ";"
    },
    {
      "Command": "E",
      "Arg1": 552,
      "Arg2": 100,
      "Arg3": 16,
      "Comment": ";"
    },
    {
      "Command": "M",
      "Arg1": 557,
      "Arg2": 5,
      "Arg3": 550,
      "Comment": "a lesser Dread to The Realm of Dread"
    },
    {
      "Command": "E",
      "Arg1": 554,
      "Arg2": 100,
      "Arg3": 12,
      "Comment": ";"
    },
    {
      "Command": "E",
      "Arg1": 550,
      "Arg2": 100,
      "Arg3": 16,
      "Comment": ";"
    },
    {
      "Command": "M",
      "Arg1": 557,
      "Arg2": 5,
      "Arg3": 557,
      "Comment": "a lesser Dread to The Realm of Dread"
    },
    {
      "Command": "E",
      "Arg1": 554,
      "Arg2": 100,
      "Arg3": 12,
      "Comment": ";"
    },
    {
      "Command": "E",
      "Arg1": 550,
      "Arg2": 100,
      "Arg3": 16,
      "Comment": ";"
    },
    {
      "Command": "M",
      "Arg1": 558,
      "Arg2": 5,
      "Arg3": 550,
      "Comment": "a Dread master to The Realm of Dread"
    },
    {
      "Command": "E",
      "Arg1": 558,
      "Arg2": 100,
      "Arg3": 1,
      "Comment": ";"
    },
    {
      "Command": "E",
      "Arg1": 555,
      "Arg2": 100,
      "Arg3": 12,
      "Comment": ";"
    },
    {
      "Command": "E",
      "Arg1": 552,
      "Arg2": 100,
      "Arg3": 16,
      "Comment": ";"
    },
    {
      "Command": "M",
      "Arg1": 558,
      "Arg2": 5,
      "Arg3": 557,
      "Comment": "a Dread master to The Realm of Dread"
    },
    {
      "Command": "E",
      "Arg1": 558,
      "Arg2": 100,
      "Arg3": 1,
      "Comment": ";"
    },
    {
      "Command": "E",
      "Arg1": 555,
      "Arg2": 100,
      "Arg3": 12,
      "Comment": ";"
    },
    {
      "Command": "E",
      "Arg1": 552,
      "Arg2": 100,
      "Arg3": 16,
      "Comment": ";"
    },
    {
      "Command": "M",
      "Arg1": 559,
      "Arg2": 5,
      "Arg3": 550,
      "Comment": "a Dread Lord to The Realm of Dread"
    },
    {
      "Command": "E",
      "Arg1": 561,
      "Arg2": 100,
      "Arg3": 1,
      "Comment": ";"
    },
    {
      "Command": "E",
      "Arg1": 556,
      "Arg2": 100,
      "Arg3": 12,
      "Comment": ";"
    },
    {
      "Command": "E",
      "Arg1": 553,
      "Arg2": 100,
      "Arg3": 16,
      "Comment": ";"
    },
    {
      "Command": "M",
      "Arg1": 559,
      "Arg2": 5,
      "Arg3": 557,
      "Comment": "a Dread Lord to The Realm of Dread"
    },
    {
      "Command": "E",
      "Arg1": 561,
      "Arg2": 100,
      "Arg3": 1,
      "Comment": ";"
    },
    {
      "Command": "E",
      "Arg1": 556,
      "Arg2": 100,
      "Arg3": 12,
      "Comment": ";"
    },
    {
      "Command": "E",
      "Arg1": 553,
      "Arg2": 100,
      "Arg3": 16,
      "Comment": ";"
    },
    {
      "Command": "M",
      "Arg1": 560,
      "Arg2": 5,
      "Arg3": 550,
      "Comment": "a Dread guard to The Realm of Dread"
    },
    {
      "Command": "E",
      "Arg1": 554,
      "Arg2": 100,
      "Arg3": 12,
      "Comment": ";"
    },
    {
      "Command": "E",
      "Arg1": 551,
      "Arg2": 100,
      "Arg3": 16,
      "Comment": ";"
    },
    {
      "Command": "M",
      "Arg1": 560,
      "Arg2": 5,
      "Arg3": 557,
      "Comment": "a Dread guard to The Realm of Dread"
    },
    {
      "Command": "E",
      "Arg1": 554,
      "Arg2": 100,
      "Arg3": 12,
      "Comment": ";"
    },
    {
      "Command": "E",
      "Arg1": 551,
      "Arg2": 100,
      "Arg3": 16,
      "Comment": ";"
    },
    {
      "Command": "M",
      "Arg1": 561,
      "Arg2": 5,
      "Arg3": 550,
      "Comment": "a Dread guardian to The Realm of Dread"
    },
    {
      "Command": "E",
      "Arg1": 554,
      "Arg2": 100,
      "Arg3": 12,
      "Comment": ";"
    },
    {
      "Command": "E",
      "Arg1": 550,
      "Arg2": 100,
      "Arg3": 16,
      "Comment": ";"
    },
    {
      "Command": "M",
      "Arg1": 561,
      "Arg2": 5,
      "Arg3": 557,
      "Comment": "a Dread guardian to The Realm of Dread"
    },
    {
      "Command": "E",
      "Arg1": 554,
      "Arg2": 100,
      "Arg3": 12,
      "Comment": ";"
    },
    {
      "Command": "E",
      "Arg1": 550,
      "Arg2": 100,
      "Arg3": 16,
      "Comment": ";"
    },
    {
      "Command": "M",
      "Arg1": 562,
      "Arg2": 5,
      "Arg3": 550,
      "Comment": "a shadow dragon to The Realm of Dread"
    },
    {
      "Command": "E",
      "Arg1": 559,
      "Arg2": 100,
      "Arg3": 14,
      "Comment": ";"
    },
    {
      "Command": "E",
      "Arg1": 552,
      "Arg2": 100,
      "Arg3": 16,
      "Comment": ";"
    },
    {
      "Command": "M",
      "Arg1": 562,
      "Arg2": 5,
      "Arg3": 557,
      "Comment": "a shadow dragon to The Realm of Dread"
    },
    {
      "Command": "E",
      "Arg1": 559,
      "Arg2": 100,
      "Arg3": 14,
      "Comment": ";"
    },
    {
      "Command": "E",
      "Arg1": 552,
      "Arg2": 100,
      "Arg3": 16,
      "Comment": ";"
    },
    {
      "Command": "M",
      "Arg1": 563,
      "Arg2": 5,
      "Arg3": 550,
      "Comment": "a smoke dragon to The Realm of Dread"
    },
    {
      "Command": "E",
      "Arg1": 560,
      "Arg2": 100,
      "Arg3": 14,
      "Comment": ";"
    },
    {
      "Command": "E",
      "Arg1": 553,
      "Arg2": 100,
      "Arg3": 16,
      "Comment": ";"
    },
    {
      "Command": "M",
      "Arg1": 563,
      "Arg2": 5,
      "Arg3": 557,
      "Comment": "a smoke dragon to The Realm of Dread"
    },
    {
      "Command": "E",
      "Arg1": 560,
      "Arg2": 100,
      "Arg3": 14,
      "Comment": ";"
    },
    {
      "Command": "E",
      "Arg1": 553,
      "Arg2": 100,
      "Arg3": 16,
      "Comment": ";"
    }
  ],
  "Shops": [],
  "Specials": [
    {
      "Vnum": 550,
      "Command": "M",
      "Spec": "spec_poison",
      "Comment": "a lesser shadow"
    },
    {
      "Vnum": 551,
      "Command": "M",
      "Spec": "spec_poison",
      "Comment": "a shadow"
    },
    {
      "Vnum": 552,
      "Command": "M",
      "Spec": "spec_breath_fire",
      "Comment": "a greater shadow"
    },
    {
      "Vnum": 553,
      "Command": "M",
      "Spec": "spec_poison",
      "Comment": "a shadowguardian"
    },
    {
      "Vnum": 554,
      "Command": "M",
      "Spec": "spec_breath_fire",
      "Comment": "a shadow lord"
    },
    {
      "Vnum": 555,
      "Command": "M",
      "Spec": "spec_poison",
      "Comment": "a Dread minion"
    },
    {
      "Vnum": 556,
      "Command": "M",
      "Spec": "spec_breath_fire",
      "Comment": "a greater Dread"
    },
    {
      "Vnum": 557,
      "Command": "M",
      "Spec": "spec_poison",
      "Comment": "a lesser Dread"
    },
    {
      "Vnum": 558,
      "Command": "M",
      "Spec": "spec_breath_fire",
      "Comment": "a Dread master"
    },
    {
      "Vnum": 559,
      "Command": "M",
      "Spec": "spec_breath_fire",
      "Comment": "a Dread Lord"
    },
    {
      "Vnum": 560,
      "Command": "M",
      "Spec": "spec_poison",
      "Comment": "a Dread guard"
    },
    {
      "Vnum": 561,
      "Command": "M",
      "Spec": "spec_poison",
      "Comment": "a Dread guardian"
    },
    {
      "Vnum": 562,
      "Command": "M",
      "Spec": "spec_breath_fire",
      "Comment": "a shadow dragon"
    },
    {
      "Vnum": 563,
      "Command": "M",
      "Spec": "spec_breath_fire",
      "Comment": "a smoke dragon"
    }
  ],
  "Helps": []
}